euphonic_sqw_models/__init__.py
euphonic_sqw_models/_version.py
euphonic_sqw_models/euphonic_wrapper.py
pace_neutrons/FunctionWrapper.py
pace_neutrons/MCR_license.txt
pace_neutrons/__init__.py
pace_neutrons/_version.py
pace_neutrons/ctfs/mexes.xz
pace_neutrons/ctfs/nomex_2021b.xz
pace_neutrons/ctfs/nomex_2022a.xz
pace_neutrons/ctfs/nomex_2022b.xz
pace_neutrons/ctfs/nomex_2023a.xz
pace_neutrons/ctfs/nomex_2023b.xz
pace_neutrons/ctfs/nomex_2024a.xz
pace_neutrons/ctfs/nomex_2024b.xz
pace_neutrons_cli/__init__.py
pace_neutrons_cli/cli.py
pace_neutrons_cli/utils.py
pace_neutrons_cli/worker.py
pace_neutrons-0.4.0.dist-info/LICENSE
pace_neutrons-0.4.0.dist-info/METADATA
pace_neutrons-0.4.0.dist-info/WHEEL
pace_neutrons-0.4.0.dist-info/entry_points.txt
pace_neutrons-0.4.0.dist-info/top_level.txt
pace_neutrons-0.4.0.dist-info/RECORD
