Metadata-Version: 2.2
Name: pace_neutrons
Version: 0.4.0
Summary: A Python wrapper around Matlab programs for inelastic neutron scattering data analysis
Home-page: https://github.com/pace-neutrons/pace-python
Author: Duc Le
Author-email: duc.le@stfc.ac.uk
Classifier: Development Status :: 2 - Pre-Alpha
Classifier: Intended Audience :: Science/Research
Classifier: License :: OSI Approved :: GNU General Public License v3 or later (GPLv3+)
Classifier: Operating System :: Microsoft :: Windows :: Windows 10
Classifier: Operating System :: POSIX :: Linux
Classifier: Programming Language :: Python :: 3
Classifier: Topic :: Scientific/Engineering :: Physics
License-File: LICENSE
Requires-Dist: six>=1.12.0
Requires-Dist: numpy>=1.7.1
Requires-Dist: appdirs>=1.4.4
Requires-Dist: ipython>=3.2.1
Requires-Dist: requests
Requires-Dist: psutil>=0.6.0
Requires-Dist: matplotlib>=2.0.0
Requires-Dist: euphonic[phonopy_reader]>=1.3.1
Requires-Dist: libpymcr>=0.2.0
Provides-Extra: interactive
Requires-Dist: matplotlib>=2.2.0; extra == "interactive"
Dynamic: author
Dynamic: author-email
Dynamic: classifier
Dynamic: description
Dynamic: description-content-type
Dynamic: home-page
Dynamic: provides-extra
Dynamic: requires-dist
Dynamic: summary
